wbwdi/__init__.py
wbwdi/config.py
wbwdi/perform_request.py
wbwdi/wdi_get.py
wbwdi/wdi_get_entities.py
wbwdi/wdi_get_income_levels.py
wbwdi/wdi_get_indicators.py
wbwdi/wdi_get_languages.py
wbwdi/wdi_get_lending_types.py
wbwdi/wdi_get_regions.py
wbwdi/wdi_get_sources.py
wbwdi/wdi_get_topics.py
wbwdi/wdi_search.py
wbwdi-1.0.1.dist-info/METADATA
wbwdi-1.0.1.dist-info/WHEEL
wbwdi-1.0.1.dist-info/RECORD
