Metadata-Version: 2.4
Name: wbwdi
Version: 1.0.1
Summary: Seamless Access to World Bank World Development Indicators with Polars
Project-URL: Repository, https://github.com/tidy-intelligence/py-wbwdi
Project-URL: Issues, https://github.com/tidy-intelligence/py-wbwdi/issues
Project-URL: Changelog, https://github.com/tidy-intelligence/py-wbwdi/blob/master/CHANGELOG.md
Author-email: Christoph Scheuch <christoph@tidy-intelligence.com>
License-Expression: MIT
Requires-Python: >=3.10
Requires-Dist: httpx>=0.28.1
Requires-Dist: polars>=1.0.0
Provides-Extra: pandas
Requires-Dist: pandas; extra == 'pandas'
Requires-Dist: pyarrow; extra == 'pandas'
